main.py
fastmcp_data_analysis_server-0.1.1.dist-info/METADATA
fastmcp_data_analysis_server-0.1.1.dist-info/WHEEL
fastmcp_data_analysis_server-0.1.1.dist-info/top_level.txt
fastmcp_data_analysis_server-0.1.1.dist-info/RECORD
