Metadata-Version: 2.4
Name: fastmcp-data-analysis-server
Version: 0.1.1
Summary: Add your description here
Requires-Python: >=3.13
Requires-Dist: fastmcp>=2.9.2
Requires-Dist: numpy>=2.3.1
Requires-Dist: pandas>=2.3.0
Requires-Dist: scipy>=1.16.0
